nvidia/__init__.py
nvidia/cuda_cccl/__init__.py
nvidia/cuda_cccl/.metadata/.sizes.txt
nvidia/cuda_cccl/.metadata/baseGuardwords.txt
nvidia/cuda_cccl/.metadata/g_guardwords.txt
nvidia/cuda_cccl/.metadata/guardword_scan_stderr.txt
nvidia/cuda_cccl/.metadata/guardword_scan_stdout.txt
nvidia/cuda_cccl/bin/__init__.py
nvidia/cuda_cccl/include/__init__.py
nvidia/cuda_cccl/include/cub/config.cuh
nvidia/cuda_cccl/include/cub/cub.cuh
nvidia/cuda_cccl/include/cub/util_allocator.cuh
nvidia/cuda_cccl/include/cub/util_arch.cuh
nvidia/cuda_cccl/include/cub/util_compiler.cuh
nvidia/cuda_cccl/include/cub/util_cpp_dialect.cuh
nvidia/cuda_cccl/include/cub/util_debug.cuh
nvidia/cuda_cccl/include/cub/util_device.cuh
nvidia/cuda_cccl/include/cub/util_macro.cuh
nvidia/cuda_cccl/include/cub/util_math.cuh
nvidia/cuda_cccl/include/cub/util_namespace.cuh
nvidia/cuda_cccl/include/cub/util_ptx.cuh
nvidia/cuda_cccl/include/cub/util_temporary_storage.cuh
nvidia/cuda_cccl/include/cub/util_type.cuh
nvidia/cuda_cccl/include/cub/util_vsmem.cuh
nvidia/cuda_cccl/include/cub/version.cuh
nvidia/cuda_cccl/include/cub/agent/agent_adjacent_difference.cuh
nvidia/cuda_cccl/include/cub/agent/agent_batch_memcpy.cuh
nvidia/cuda_cccl/include/cub/agent/agent_for.cuh
nvidia/cuda_cccl/include/cub/agent/agent_histogram.cuh
nvidia/cuda_cccl/include/cub/agent/agent_merge.cuh
nvidia/cuda_cccl/include/cub/agent/agent_merge_sort.cuh
nvidia/cuda_cccl/include/cub/agent/agent_radix_sort_downsweep.cuh
nvidia/cuda_cccl/include/cub/agent/agent_radix_sort_histogram.cuh
nvidia/cuda_cccl/include/cub/agent/agent_radix_sort_onesweep.cuh
nvidia/cuda_cccl/include/cub/agent/agent_radix_sort_upsweep.cuh
nvidia/cuda_cccl/include/cub/agent/agent_reduce.cuh
nvidia/cuda_cccl/include/cub/agent/agent_reduce_by_key.cuh
nvidia/cuda_cccl/include/cub/agent/agent_rle.cuh
nvidia/cuda_cccl/include/cub/agent/agent_scan.cuh
nvidia/cuda_cccl/include/cub/agent/agent_scan_by_key.cuh
nvidia/cuda_cccl/include/cub/agent/agent_segment_fixup.cuh
nvidia_cuda_cccl_cu12-12.9.27.dist-info/License.txt
nvidia_cuda_cccl_cu12-12.9.27.dist-info/METADATA
nvidia_cuda_cccl_cu12-12.9.27.dist-info/WHEEL
nvidia_cuda_cccl_cu12-12.9.27.dist-info/top_level.txt
nvidia_cuda_cccl_cu12-12.9.27.dist-info/RECORD
